flex_menu/__init__.py
flex_menu/apps.py
flex_menu/checks.py
flex_menu/management/__init__.py
flex_menu/management/commands/__init__.py
flex_menu/management/commands/render_menu.py
flex_menu/menu.py
flex_menu/renderers.py
flex_menu/templatetags/__init__.py
flex_menu/templatetags/flex_menu.py
flex_menu/utils.py
django_flex_menus-0.4.1.dist-info/LICENSE
django_flex_menus-0.4.1.dist-info/METADATA
django_flex_menus-0.4.1.dist-info/WHEEL
django_flex_menus-0.4.1.dist-info/RECORD
