Metadata-Version: 2.1
Name: django-flex-menus
Version: 0.4.1
Summary: Flexible site menus for Django
Home-page: https://github.com/SamuelJennings/django-flex-menus
License: MIT
Author: Samuel Jennings
Author-email: samuel.scott.jennings@gmail.com
Requires-Python: >=3.10,<4.0
Classifier: License :: OSI Approved :: MIT License
Classifier: Programming Language :: Python :: 3
Classifier: Programming Language :: Python :: 3.10
Classifier: Programming Language :: Python :: 3.11
Classifier: Programming Language :: Python :: 3.12
Requires-Dist: anytree (>2)
Requires-Dist: django (>=4.2,<5.3)
